{
    "grids": [
        {
            "gridID": "Pulls2",
            "gridTitle": "Pulls 2",
            "gridSize": {"height": 2, "columns": 6, "rows": 6},
            "layers": [
                {
                    "layout": [
                        "......",
                        "......",
                        "......",
                        "......",
                        "......",
                        "......"
                    ]
                },
                {
                    "layout": [
                        "      ",
                        "  TTT ",
                        " PW W ",
                        "  BBB ",
                        "      ",
                        "      "
                    ]
                }
            ]
        }
    ]
}